minishogilib-0.6.17.dist-info/METADATA
minishogilib-0.6.17.dist-info/WHEEL
minishogilib/__init__.py
minishogilib/minishogilib.abi3.so
minishogilib-0.6.17.dist-info/RECORD
