Metadata-Version: 2.1
Name: minishogilib
Version: 0.6.17
Author: nyashiki
